LICENSE
MANIFEST.in
README.rst
setup.py
django_mail_confirmation.egg-info/PKG-INFO
django_mail_confirmation.egg-info/SOURCES.txt
django_mail_confirmation.egg-info/dependency_links.txt
django_mail_confirmation.egg-info/top_level.txt
mail_confirmation/__init__.py
mail_confirmation/admin.py
mail_confirmation/models.py
mail_confirmation/signals.py
mail_confirmation/tasks.py
mail_confirmation/urls.py
mail_confirmation/utils.py
mail_confirmation/views.py
mail_confirmation/migrations/0001_initial.py
mail_confirmation/migrations/0002_mailconfirmation_forusers.py
mail_confirmation/migrations/__init__.py
mail_confirmation/south_migrations/0001_initial.py
mail_confirmation/south_migrations/0002_auto.py
mail_confirmation/south_migrations/__init__.py
mail_confirmation/tests/__init__.py
mail_confirmation/tests/models.py
mail_confirmation/tests/settings.py
mail_confirmation/tests/tests.py
mail_confirmation/tests/urls.py