Metadata-Version: 1.1
Name: django-mail-confirmation
Version: 1.2.6
Summary: A general django user mail confirmation app usable with multiple models at the same time.
Home-page: http://v.licheni.net/drc/django-mail_confirmation.git
Author: Davide Riccardo Caliendo
Author-email: davide.licheni.net
License: GPLv3 License
Platform: UNKNOWN
Classifier: Environment :: Web Environment
Classifier: Framework :: Django
Classifier: Intended Audience :: Developers
Classifier: License :: OSI Approved :: GNU General Public License v3 (GPLv3)
Classifier: Operating System :: OS Independent
Classifier: Programming Language :: Python
Classifier: Programming Language :: Python :: 2.6
Classifier: Programming Language :: Python :: 2.7
Classifier: Topic :: Internet :: WWW/HTTP
Classifier: Topic :: Internet :: WWW/HTTP :: Dynamic Content
